{
  "textures": {
    "particle": "#wallpaper"
  },
  "elements": [
    {
      "from": [
        0,
        0,
        0
      ],
      "to": [
        16,
        16,
        1
      ],
      "faces": {
        "down": {
          "texture": "#wallpaper"
        },
        "up": {
          "texture": "#wallpaper"
        },
        "north": {
          "texture": "#wallpaper"
        },
        "south": {
          "texture": "#wallpaper"
        },
        "west": {
          "texture": "#wallpaper"
        },
        "east": {
          "texture": "#wallpaper"
        }
      }
    }
  ]
}